factory_boy_extra/__init__.py
factory_boy_extra/async_sqlalchemy_factory.py
factory_boy_extra/tortoise_factory.py
factory_boy_extra-0.1.3.dist-info/LICENSE
factory_boy_extra-0.1.3.dist-info/WHEEL
factory_boy_extra-0.1.3.dist-info/METADATA
factory_boy_extra-0.1.3.dist-info/RECORD
