Metadata-Version: 2.1
Name: factory-boy-extra
Version: 0.1.3
Summary: 
Home-page: https://github.com/s3rius/factory_boy_extra
Keywords: ORM,SQLAlchemy,Tortoise-ORM,Factory,factory_boy
Author: Pavel Kirilin
Author-email: win10@list.ru
Requires-Python: >=3.8.7,<4.0.0
Classifier: Environment :: Plugins
Classifier: License :: OSI Approved :: MIT License
Classifier: Programming Language :: Python :: 3
Classifier: Programming Language :: Python :: 3.9
Classifier: Topic :: Database
Requires-Dist: factory-boy (>=3.2.0,<4.0.0)
Project-URL: Repository, https://github.com/s3rius/factory_boy_extra
